aspectp.py
aspectp-1.0.1.dist-info/LICENSE
aspectp-1.0.1.dist-info/METADATA
aspectp-1.0.1.dist-info/WHEEL
aspectp-1.0.1.dist-info/top_level.txt
aspectp-1.0.1.dist-info/RECORD
