Metadata-Version: 2.1
Name: aspectp
Version: 1.0.1
Summary: Aspect Oriented Programming in Python
Author-email: Gabriele Maurina <gabrielemaurina95@gmail.com>
Project-URL: Homepage, https://github.com/GabrieleMaurina/aspectp
Classifier: Programming Language :: Python :: 3
Classifier: License :: OSI Approved :: GNU General Public License v3 (GPLv3)
Classifier: Operating System :: OS Independent
Requires-Python: >=3.11
License-File: LICENSE
